Http2XieyiZhongwenfanyi/README.md
Http2XieyiZhongwenfanyi/__init__.py
Http2XieyiZhongwenfanyi/__main__.py
Http2XieyiZhongwenfanyi/file.epub
Http2XieyiZhongwenfanyi/index.html
Http2XieyiZhongwenfanyi/css/__init__.py
Http2XieyiZhongwenfanyi/css/annotations.css
Http2XieyiZhongwenfanyi/css/main.css
Http2XieyiZhongwenfanyi/css/normalize.css
Http2XieyiZhongwenfanyi/css/popup.css
Http2XieyiZhongwenfanyi/font/__init__.py
Http2XieyiZhongwenfanyi/font/fontello.eot
Http2XieyiZhongwenfanyi/font/fontello.svg
Http2XieyiZhongwenfanyi/font/fontello.ttf
Http2XieyiZhongwenfanyi/font/fontello.woff
Http2XieyiZhongwenfanyi/img/__init__.py
Http2XieyiZhongwenfanyi/img/annotator-glyph-sprite.png
Http2XieyiZhongwenfanyi/img/annotator-icon-sprite.png
Http2XieyiZhongwenfanyi/img/apple-touch-icon.png
Http2XieyiZhongwenfanyi/img/cancelfullscreen.png
Http2XieyiZhongwenfanyi/img/close.png
Http2XieyiZhongwenfanyi/img/fullscreen.png
Http2XieyiZhongwenfanyi/img/loader.gif
Http2XieyiZhongwenfanyi/img/menu-icon.png
Http2XieyiZhongwenfanyi/img/save.png
Http2XieyiZhongwenfanyi/img/saved.png
Http2XieyiZhongwenfanyi/img/settings-s.png
Http2XieyiZhongwenfanyi/img/settings.png
Http2XieyiZhongwenfanyi/img/star.png
Http2XieyiZhongwenfanyi/js/__init__.py
Http2XieyiZhongwenfanyi/js/epub.js
Http2XieyiZhongwenfanyi/js/epub.min.js
Http2XieyiZhongwenfanyi/js/epub.min.map
Http2XieyiZhongwenfanyi/js/hooks.min.js
Http2XieyiZhongwenfanyi/js/hooks.min.map
Http2XieyiZhongwenfanyi/js/reader.js
Http2XieyiZhongwenfanyi/js/reader.js.map
Http2XieyiZhongwenfanyi/js/reader.min.js
Http2XieyiZhongwenfanyi/js/reader.min.map
Http2XieyiZhongwenfanyi/js/hooks/__init__.py
Http2XieyiZhongwenfanyi/js/hooks/extensions/__init__.py
Http2XieyiZhongwenfanyi/js/hooks/extensions/highlight.js
Http2XieyiZhongwenfanyi/js/libs/__init__.py
Http2XieyiZhongwenfanyi/js/libs/jquery.min.js
Http2XieyiZhongwenfanyi/js/libs/localforage.min.js
Http2XieyiZhongwenfanyi/js/libs/screenfull.js
Http2XieyiZhongwenfanyi/js/libs/screenfull.min.js
http2_xieyi_zhongwenfanyi-2024.3.2.0.dist-info/METADATA
http2_xieyi_zhongwenfanyi-2024.3.2.0.dist-info/WHEEL
http2_xieyi_zhongwenfanyi-2024.3.2.0.dist-info/entry_points.txt
http2_xieyi_zhongwenfanyi-2024.3.2.0.dist-info/top_level.txt
http2_xieyi_zhongwenfanyi-2024.3.2.0.dist-info/RECORD
